snub/__init__.py
snub/__main__.py
snub/api.py
snub/base.py
snub/dns.py
snub/snub.py
snub/sync.py
snub/data/dns.spam.yml
snub/data/text.blackhole.yml
snub/data/text.static.yml
snub-0.0.3.dist-info/LICENSE.md
snub-0.0.3.dist-info/METADATA
snub-0.0.3.dist-info/WHEEL
snub-0.0.3.dist-info/entry_points.txt
snub-0.0.3.dist-info/top_level.txt
snub-0.0.3.dist-info/RECORD
