Metadata-Version: 2.1
Name: snub
Version: 0.0.3
Summary: Snup is a python package to check IPs, Hashes, Emails, Domains, or URLs against blackhole lists and DNS services.
Home-page: https://github.com/swimlane/snub
Author: Josh Rickard
Author-email: josh.rickard@swimlane.com
License: MIT
Keywords: blackhole python api ip email hash domain url
Platform: UNKNOWN
Requires-Dist: requests
Requires-Dist: pyyaml
Requires-Dist: flask-restful
Requires-Dist: hopper
